{
    "p2kwiet19724036341549_cotizadorEnviar2_preshow_seq0": {
        "id": "p2kwiet19724036341549_cotizadorEnviar2_preshow_seq0",
        "type": "ACTION_SEQUENCE",
        "params": [{
            "name": "eventobject",
            "value": "eventobject"
        }],
        "language": "js",
        "actions": [{
            "id": "customcode_preshow_1966019724036349363",
            "type": "INVOKE_FUNCTION",
            "sequenceKUID": "validarPreShow",
            "display": "validarPreShow",
            "inputparams": []
        }]
    }
}